{"142":{"SubRegions":{"34":{"Sub_region_Name":"Southern Asia","Subregions":[]},"145":{"Sub_region_Name":"Western Asia","Subregions":[]},"35":{"Sub_region_Name":"South-eastern Asia","Subregions":[]},"30":{"Sub_region_Name":"Eastern Asia","Subregions":[]},"143":{"Sub_region_Name":"Central Asia","Subregions":[]}},"Subregions":{"34":{"IntermediateRegions":{"":{"Intermediate_Region_Name":null,"Countries":[{"CountryName":"Sri Lanka","Code":"LKA"}]}}},"145":{"IntermediateRegions":{"":{"Intermediate_Region_Name":null,"Countries":[{"CountryName":"Yemen","Code":"YEM"}]}}},"35":{"IntermediateRegions":{"":{"Intermediate_Region_Name":null,"Countries":[{"CountryName":"Viet Nam","Code":"VNM"}]}}},"30":{"IntermediateRegions":{"":{"Intermediate_Region_Name":null,"Countries":[{"CountryName":"Republic of Korea","Code":"KOR"}]}}},"143":{"IntermediateRegions":{"":{"Intermediate_Region_Name":null,"Countries":[{"CountryName":"Uzbekistan","Code":"UZB"}]}}}}},"150":{"SubRegions":{"154":{"Sub_region_Name":"Northern Europe","Subregions":[]},"39":{"Sub_region_Name":"Southern Europe","Subregions":[]},"155":{"Sub_region_Name":"Western Europe","Subregions":[]},"151":{"Sub_region_Name":"Eastern Europe","Subregions":[]}},"Subregions":{"154":{"IntermediateRegions":{"":{"Intermediate_Region_Name":null,"Countries":[{"CountryName":"United Kingdom of Great Britain and Northern Ireland","Code":"GBR"}]},"830":{"Intermediate_Region_Name":"Channel Islands","Countries":[{"CountryName":"Sark","Code":null}]}}},"39":{"IntermediateRegions":{"":{"Intermediate_Region_Name":null,"Countries":[{"CountryName":"Spain","Code":"ESP"}]}}},"155":{"IntermediateRegions":{"":{"Intermediate_Region_Name":null,"Countries":[{"CountryName":"Switzerland","Code":"CHE"}]}}},"151":{"IntermediateRegions":{"":{"Intermediate_Region_Name":null,"Countries":[{"CountryName":"Ukraine","Code":"UKR"}]}}}}},"2":{"SubRegions":{"15":{"Sub_region_Name":"Northern Africa","Subregions":[]},"202":{"Sub_region_Name":"Sub-Saharan Africa","Subregions":[]}},"Subregions":{"15":{"IntermediateRegions":{"":{"Intermediate_Region_Name":null,"Countries":[{"CountryName":"Western Sahara","Code":"ESH"}]}}},"202":{"IntermediateRegions":{"17":{"Intermediate_Region_Name":"Middle Africa","Countries":[{"CountryName":"Sao Tome and Principe","Code":"STP"}]},"11":{"Intermediate_Region_Name":"Western Africa","Countries":[{"CountryName":"Togo","Code":"TGO"}]},"18":{"Intermediate_Region_Name":"Southern Africa","Countries":[{"CountryName":"South Africa","Code":"ZAF"}]},"14":{"Intermediate_Region_Name":"Eastern Africa","Countries":[{"CountryName":"Zimbabwe","Code":"ZWE"}]}}}}},"9":{"SubRegions":{"61":{"Sub_region_Name":"Polynesia","Subregions":[]},"53":{"Sub_region_Name":"Australia and New Zealand","Subregions":[]},"54":{"Sub_region_Name":"Melanesia","Subregions":[]},"57":{"Sub_region_Name":"Micronesia","Subregions":[]}},"Subregions":{"61":{"IntermediateRegions":{"":{"Intermediate_Region_Name":null,"Countries":[{"CountryName":"Tuvalu","Code":"TUV"}]}}},"53":{"IntermediateRegions":{"":{"Intermediate_Region_Name":null,"Countries":[{"CountryName":"Norfolk Island","Code":"NFK"}]}}},"54":{"IntermediateRegions":{"":{"Intermediate_Region_Name":null,"Countries":[{"CountryName":"Vanuatu","Code":"VUT"}]}}},"57":{"IntermediateRegions":{"":{"Intermediate_Region_Name":null,"Countries":[{"CountryName":"United States Minor Outlying Islands","Code":"UMI"}]}}}}},"19":{"SubRegions":{"419":{"Sub_region_Name":"Latin America and the Caribbean","Subregions":[]},"21":{"Sub_region_Name":"Northern America","Subregions":[]}},"Subregions":{"419":{"IntermediateRegions":{"29":{"Intermediate_Region_Name":"Caribbean","Countries":[{"CountryName":"United States Virgin Islands","Code":"VIR"}]},"5":{"Intermediate_Region_Name":"South America","Countries":[{"CountryName":"Venezuela (Bolivarian Republic of)","Code":"VEN"}]},"13":{"Intermediate_Region_Name":"Central America","Countries":[{"CountryName":"Panama","Code":"PAN"}]}}},"21":{"IntermediateRegions":{"":{"Intermediate_Region_Name":null,"Countries":[{"CountryName":"United States of America","Code":"USA"}]}}}}}}